codemate.py
jenix.py
termind.py
jenix-0.1.3.dist-info/METADATA
jenix-0.1.3.dist-info/WHEEL
jenix-0.1.3.dist-info/entry_points.txt
jenix-0.1.3.dist-info/top_level.txt
jenix-0.1.3.dist-info/RECORD
