Metadata-Version: 2.4
Name: jenix
Version: 0.1.3
Summary: An agentic coding assistant using local LLMs from Ollama
Home-page: https://github.com/Abhijeetsingh610/Jenix.git
Author: Abhijeet Singh
Author-email: abhis6102003@gmail.com
Classifier: Programming Language :: Python :: 3
Classifier: License :: OSI Approved :: MIT License
Classifier: Operating System :: OS Independent
Requires-Python: >=3.6
Requires-Dist: requests>=2.25.0
Requires-Dist: rich
Requires-Dist: anthropic
Requires-Dist: google-generativeai
Dynamic: author
Dynamic: author-email
Dynamic: classifier
Dynamic: description
Dynamic: description-content-type
Dynamic: home-page
Dynamic: requires-dist
Dynamic: requires-python
Dynamic: summary
